{
  "entities": [
    {
      "name": "All Of Us Becoming A World Church",
      "type": "PERSON",
      "metadata": {},
      "salience": 0.92406619,
      "mentions": [
        {
          "text": {
            "content": "World Church",
            "beginOffset": 11
          }
        },
        {
          "text": {
            "content": "The Poor",
            "beginOffset": 33
          }
        },
        {
          "text": {
            "content": "All Of Us Becoming A World Church",
            "beginOffset": 43
          }
        },
        {
          "text": {
            "content": "The Poor",
            "beginOffset": 86
          }
        },
        {
          "text": {
            "content": "The Poor",
            "beginOffset": 148
          }
        },
        {
          "text": {
            "content": "All Of Us",
            "beginOffset": 158
          }
        }
      ]
    },
    {
      "name": "All Of Us England Becoming A World Church",
      "type": "WORK_OF_ART",
      "metadata": {},
      "salience": 0.045663346,
      "mentions": [
        {
          "text": {
            "content": "All Of Us England  Becoming A World Church",
            "beginOffset": 96
          }
        }
      ]
    },
    {
      "name": "Eugene England",
      "type": "LOCATION",
      "metadata": {},
      "salience": 0.03027047,
      "mentions": [
        {
          "text": {
            "content": "Eugene England",
            "beginOffset": 168
          }
        }
      ]
    }
  ],
  "language": "en"
}
