{
  "entities": [
    {
      "name": "Alfred North Whitehead&",
      "type": "PERSON",
      "metadata": {},
      "salience": 0.06699162,
      "mentions": [
        {
          "text": {
            "content": "Alfred North Whitehead&",
            "beginOffset": 73
          }
        },
        {
          "text": {
            "content": "Whitehead&",
            "beginOffset": 298
          }
        },
        {
          "text": {
            "content": "Alfred North Whitehead&",
            "beginOffset": 1336
          }
        },
        {
          "text": {
            "content": "Whitehead&",
            "beginOffset": 1561
          }
        }
      ]
    },
    {
      "name": "McLachlan",
      "type": "PERSON",
      "metadata": {
        "wikipedia_url": "http://en.wikipedia.org/wiki/Sarah_McLachlan"
      },
      "salience": 0.02008054,
      "mentions": [
        {
          "text": {
            "content": "McLachlan",
            "beginOffset": 865
          }
        }
      ]
    },
    {
      "name": "MORMONISM",
      "type": "OTHER",
      "metadata": {
        "wikipedia_url": "http://en.wikipedia.org/wiki/Mormonism"
      },
      "salience": 0.014925686,
      "mentions": [
        {
          "text": {
            "content": "MORMONISM",
            "beginOffset": 42
          }
        }
      ]
    },
    {
      "name": "Process and Reality",
      "type": "WORK_OF_ART",
      "metadata": {},
      "salience": 0.011706466,
      "mentions": [
        {
          "text": {
            "content": "Process and Reality",
            "beginOffset": 104
          }
        },
        {
          "text": {
            "content": "Process and Reality",
            "beginOffset": 1367
          }
        }
      ]
    },
    {
      "name": "Brian Birch",
      "type": "PERSON",
      "metadata": {},
      "salience": 0.0041121366,
      "mentions": [
        {
          "text": {
            "content": "Brian Birch",
            "beginOffset": 925
          }
        }
      ]
    },
    {
      "name": "God",
      "type": "PERSON",
      "metadata": {
        "wikipedia_url": "http://en.wikipedia.org/wiki/God"
      },
      "salience": 0.00270585,
      "mentions": [
        {
          "text": {
            "content": "God",
            "beginOffset": 457
          }
        },
        {
          "text": {
            "content": "God",
            "beginOffset": 775
          }
        }
      ]
    },
    {
      "name": "LDS",
      "type": "ORGANIZATION",
      "metadata": {
        "wikipedia_url": "http://en.wikipedia.org/wiki/The_Church_of_Jesus_Christ_of_Latter-day_Saints"
      },
      "salience": 0.0020811132,
      "mentions": [
        {
          "text": {
            "content": "LDS",
            "beginOffset": 636
          }
        },
        {
          "text": {
            "content": "LDS",
            "beginOffset": 830
          }
        }
      ]
    },
    {
      "name": "Kevin Winters",
      "type": "PERSON",
      "metadata": {},
      "salience": 0.0013326008,
      "mentions": [
        {
          "text": {
            "content": "Kevin Winters",
            "beginOffset": 876
          }
        }
      ]
    },
    {
      "name": "Blake T. Ostler",
      "type": "PERSON",
      "metadata": {
        "wikipedia_url": "http://en.wikipedia.org/wiki/Blake_Ostler"
      },
      "salience": 0.0013326008,
      "mentions": [
        {
          "text": {
            "content": "Blake T. Ostler",
            "beginOffset": 891
          }
        }
      ]
    },
    {
      "name": "Dan Wotherspoon",
      "type": "PERSON",
      "metadata": {},
      "salience": 0.0013326008,
      "mentions": [
        {
          "text": {
            "content": "Dan Wotherspoon",
            "beginOffset": 908
          }
        }
      ]
    },
    {
      "name": "&hellip",
      "type": "OTHER",
      "metadata": {},
      "salience": 0.0009557911,
      "mentions": [
        {
          "text": {
            "content": "&hellip",
            "beginOffset": 1703
          }
        }
      ]
    }
  ],
  "language": "en"
}
