{
  "entities": [
    {
      "name": "Previews of Coming Attractions",
      "type": "WORK_OF_ART",
      "metadata": {
        "wikipedia_url": "http://en.wikipedia.org/wiki/Trailer_(promotion)"
      },
      "salience": 0.062707245,
      "mentions": [
        {
          "text": {
            "content": "Previews of Coming Attractions",
            "beginOffset": 28
          }
        },
        {
          "text": {
            "content": "Previews of Coming Attractions",
            "beginOffset": 87
          }
        },
        {
          "text": {
            "content": "Previews of Coming Attractions",
            "beginOffset": 1257
          }
        }
      ]
    },
    {
      "name": "The Untold Story of Black Mormons",
      "type": "WORK_OF_ART",
      "metadata": {},
      "salience": 0.054309446,
      "mentions": [
        {
          "text": {
            "content": "The Untold Story of Black Mormons",
            "beginOffset": 328
          }
        },
        {
          "text": {
            "content": "The Untold Story of Black Mormons",
            "beginOffset": 1498
          }
        }
      ]
    },
    {
      "name": "Sunstone Short Film Contest",
      "type": "EVENT",
      "metadata": {},
      "salience": 0.025288269,
      "mentions": [
        {
          "text": {
            "content": "Sunstone Short Film Contest",
            "beginOffset": 198
          }
        },
        {
          "text": {
            "content": "Sunstone Short Film Contest",
            "beginOffset": 1368
          }
        }
      ]
    },
    {
      "name": "LDS",
      "type": "ORGANIZATION",
      "metadata": {
        "wikipedia_url": "http://en.wikipedia.org/wiki/The_Church_of_Jesus_Christ_of_Latter-day_Saints"
      },
      "salience": 0.01344341,
      "mentions": [
        {
          "text": {
            "content": "LDS",
            "beginOffset": 279
          }
        },
        {
          "text": {
            "content": "LDS",
            "beginOffset": 1449
          }
        }
      ]
    },
    {
      "name": "The Natural Family",
      "type": "PERSON",
      "metadata": {},
      "salience": 0.0058786226,
      "mentions": [
        {
          "text": {
            "content": "The Natural Family",
            "beginOffset": 558
          }
        }
      ]
    },
    {
      "name": "Joseph Smith",
      "type": "PERSON",
      "metadata": {
        "wikipedia_url": "http://en.wikipedia.org/wiki/Joseph_Smith"
      },
      "salience": 0.0056292056,
      "mentions": [
        {
          "text": {
            "content": "Smith",
            "beginOffset": 477
          }
        },
        {
          "text": {
            "content": "Joseph Smith",
            "beginOffset": 540
          }
        }
      ]
    },
    {
      "name": "Natural Family",
      "type": "PERSON",
      "metadata": {},
      "salience": 0.0055716448,
      "mentions": [
        {
          "text": {
            "content": "Natural Family",
            "beginOffset": 656
          }
        }
      ]
    },
    {
      "name": "Saints",
      "type": "ORGANIZATION",
      "metadata": {
        "wikipedia_url": "http://en.wikipedia.org/wiki/Saint"
      },
      "salience": 0.0044895359,
      "mentions": [
        {
          "text": {
            "content": "Saints",
            "beginOffset": 443
          }
        }
      ]
    },
    {
      "name": "Kanab",
      "type": "LOCATION",
      "metadata": {
        "wikipedia_url": "http://en.wikipedia.org/wiki/Kanab,_Utah"
      },
      "salience": 0.0044895359,
      "mentions": [
        {
          "text": {
            "content": "Kanab",
            "beginOffset": 612
          }
        }
      ]
    },
    {
      "name": "Denhalter",
      "type": "PERSON",
      "metadata": {},
      "salience": 0.0043370617,
      "mentions": [
        {
          "text": {
            "content": "Denhalter",
            "beginOffset": 913
          }
        }
      ]
    },
    {
      "name": "Utah",
      "type": "LOCATION",
      "metadata": {
        "wikipedia_url": "http://en.wikipedia.org/wiki/Utah"
      },
      "salience": 0.0042549861,
      "mentions": [
        {
          "text": {
            "content": "Utah",
            "beginOffset": 619
          }
        }
      ]
    },
    {
      "name": "God",
      "type": "PERSON",
      "metadata": {
        "wikipedia_url": "http://en.wikipedia.org/wiki/God"
      },
      "salience": 0.0035263253,
      "mentions": [
        {
          "text": {
            "content": "God",
            "beginOffset": 820
          }
        }
      ]
    },
    {
      "name": "&hellip",
      "type": "OTHER",
      "metadata": {},
      "salience": 0.0024264948,
      "mentions": [
        {
          "text": {
            "content": "&hellip",
            "beginOffset": 1553
          }
        }
      ]
    },
    {
      "name": "Jeremy",
      "type": "PERSON",
      "metadata": {},
      "salience": 0.0010452234,
      "mentions": [
        {
          "text": {
            "content": "Jeremy",
            "beginOffset": 973
          }
        }
      ]
    }
  ],
  "language": "en"
}
