{
  "entities": [
    {
      "name": "Steven Fales",
      "type": "PERSON",
      "metadata": {
        "wikipedia_url": "http://en.wikipedia.org/wiki/Steven_Fales"
      },
      "salience": 0.32992733,
      "mentions": [
        {
          "text": {
            "content": "Steven Fales",
            "beginOffset": 136
          }
        },
        {
          "text": {
            "content": "Steven",
            "beginOffset": 519
          }
        },
        {
          "text": {
            "content": "Steven",
            "beginOffset": 644
          }
        },
        {
          "text": {
            "content": "Steven Fales",
            "beginOffset": 1350
          }
        }
      ]
    },
    {
      "name": "Sunstone",
      "type": "ORGANIZATION",
      "metadata": {
        "wikipedia_url": "http://en.wikipedia.org/wiki/Sunstone_(magazine)"
      },
      "salience": 0.047941167,
      "mentions": [
        {
          "text": {
            "content": "Sunstone",
            "beginOffset": 160
          }
        },
        {
          "text": {
            "content": "Sunstone",
            "beginOffset": 1374
          }
        }
      ]
    },
    {
      "name": "Mormon American Princess Fresh",
      "type": "ORGANIZATION",
      "metadata": {},
      "salience": 0.028122555,
      "mentions": [
        {
          "text": {
            "content": "Mormon American Princess Fresh",
            "beginOffset": 43
          }
        },
        {
          "text": {
            "content": "Mormon American Princess",
            "beginOffset": 618
          }
        },
        {
          "text": {
            "content": "Mormon American Princess Fresh",
            "beginOffset": 1257
          }
        }
      ]
    },
    {
      "name": "Mormon American Princess Reading",
      "type": "WORK_OF_ART",
      "metadata": {},
      "salience": 0.019708393,
      "mentions": [
        {
          "text": {
            "content": "Mormon American Princess Reading",
            "beginOffset": 9
          }
        }
      ]
    },
    {
      "name": "Las Vegas",
      "type": "LOCATION",
      "metadata": {
        "wikipedia_url": "http://en.wikipedia.org/wiki/Las_Vegas"
      },
      "salience": 0.016401112,
      "mentions": [
        {
          "text": {
            "content": "Las Vegas",
            "beginOffset": 502
          }
        }
      ]
    },
    {
      "name": "Steven&",
      "type": "PERSON",
      "metadata": {},
      "salience": 0.015391524,
      "mentions": [
        {
          "text": {
            "content": "Steven&",
            "beginOffset": 334
          }
        },
        {
          "text": {
            "content": "Steven&",
            "beginOffset": 1548
          }
        }
      ]
    },
    {
      "name": "God",
      "type": "PERSON",
      "metadata": {
        "wikipedia_url": "http://en.wikipedia.org/wiki/God"
      },
      "salience": 0.011080623,
      "mentions": [
        {
          "text": {
            "content": "God",
            "beginOffset": 254
          }
        },
        {
          "text": {
            "content": "God",
            "beginOffset": 1468
          }
        }
      ]
    },
    {
      "name": "Mormon Boy",
      "type": "PERSON",
      "metadata": {},
      "salience": 0.0082927905,
      "mentions": [
        {
          "text": {
            "content": "Mormon Boy",
            "beginOffset": 124
          }
        },
        {
          "text": {
            "content": "Mormon Boy",
            "beginOffset": 1338
          }
        }
      ]
    },
    {
      "name": "Off-Broadway",
      "type": "ORGANIZATION",
      "metadata": {
        "wikipedia_url": "http://en.wikipedia.org/wiki/Off-Broadway"
      },
      "salience": 0.0074157449,
      "mentions": [
        {
          "text": {
            "content": "Off-Broadway",
            "beginOffset": 87
          }
        },
        {
          "text": {
            "content": "Off-Broadway",
            "beginOffset": 1301
          }
        }
      ]
    },
    {
      "name": "American",
      "type": "PERSON",
      "metadata": {
        "wikipedia_url": "http://en.wikipedia.org/wiki/United_States"
      },
      "salience": 0.0054584136,
      "mentions": [
        {
          "text": {
            "content": "American",
            "beginOffset": 482
          }
        }
      ]
    },
    {
      "name": "Reading",
      "type": "WORK_OF_ART",
      "metadata": {
        "wikipedia_url": "http://en.wikipedia.org/wiki/Reading_(process)"
      },
      "salience": 0.0042534359,
      "mentions": [
        {
          "text": {
            "content": "Reading",
            "beginOffset": 1248
          }
        }
      ]
    },
    {
      "name": "Utah",
      "type": "LOCATION",
      "metadata": {
        "wikipedia_url": "http://en.wikipedia.org/wiki/Utah"
      },
      "salience": 0.0041684452,
      "mentions": [
        {
          "text": {
            "content": "Utah",
            "beginOffset": 464
          }
        }
      ]
    },
    {
      "name": "Manhattan",
      "type": "LOCATION",
      "metadata": {
        "wikipedia_url": "http://en.wikipedia.org/wiki/Manhattan"
      },
      "salience": 0.0035600604,
      "mentions": [
        {
          "text": {
            "content": "Manhattan",
            "beginOffset": 588
          }
        }
      ]
    },
    {
      "name": "Higher Power",
      "type": "OTHER",
      "metadata": {
        "wikipedia_url": "http://en.wikipedia.org/wiki/Deity"
      },
      "salience": 0.0032840502,
      "mentions": [
        {
          "text": {
            "content": "Higher Power",
            "beginOffset": 751
          }
        }
      ]
    },
    {
      "name": "Stephen Stephen",
      "type": "PERSON",
      "metadata": {},
      "salience": 0.001554304,
      "mentions": [
        {
          "text": {
            "content": "Stephen  Stephen",
            "beginOffset": 1057
          }
        }
      ]
    },
    {
      "name": "Provo Utah Stephen",
      "type": "LOCATION",
      "metadata": {},
      "salience": 0.0010962251,
      "mentions": [
        {
          "text": {
            "content": "Provo Utah Stephen",
            "beginOffset": 1197
          }
        }
      ]
    },
    {
      "name": "Alan",
      "type": "PERSON",
      "metadata": {},
      "salience": 0.00083685759,
      "mentions": [
        {
          "text": {
            "content": "Alan",
            "beginOffset": 1016
          }
        }
      ]
    }
  ],
  "language": "en"
}
