{
  "entities": [
    {
      "name": "Fundamentalist Church of Jesus Christ of Latter Day Saints",
      "type": "ORGANIZATION",
      "metadata": {
        "wikipedia_url": "http://en.wikipedia.org/wiki/Fundamentalist_Church_of_Jesus_Christ_of_Latter-Day_Saints"
      },
      "salience": 0.1366747,
      "mentions": [
        {
          "text": {
            "content": "FLDS",
            "beginOffset": 23
          }
        },
        {
          "text": {
            "content": "FLDS",
            "beginOffset": 57
          }
        },
        {
          "text": {
            "content": "FLDS",
            "beginOffset": 802
          }
        },
        {
          "text": {
            "content": "Fundamentalist Church of Jesus Christ of Latter Day Saints",
            "beginOffset": 361
          }
        }
      ]
    },
    {
      "name": "Texas Child Protective Services",
      "type": "ORGANIZATION",
      "metadata": {},
      "salience": 0.023054251,
      "mentions": [
        {
          "text": {
            "content": "Texas Child Protective Services",
            "beginOffset": 158
          }
        },
        {
          "text": {
            "content": "Texas Child Protective Services",
            "beginOffset": 903
          }
        }
      ]
    },
    {
      "name": "Texas",
      "type": "LOCATION",
      "metadata": {
        "wikipedia_url": "http://en.wikipedia.org/wiki/Texas"
      },
      "salience": 0.016974993,
      "mentions": [
        {
          "text": {
            "content": "Texas",
            "beginOffset": 17
          }
        },
        {
          "text": {
            "content": "Texas",
            "beginOffset": 51
          }
        },
        {
          "text": {
            "content": "Texas",
            "beginOffset": 796
          }
        }
      ]
    },
    {
      "name": "Yearning for Zion",
      "type": "ORGANIZATION",
      "metadata": {
        "wikipedia_url": "http://en.wikipedia.org/wiki/YFZ_Ranch"
      },
      "salience": 0.0062622591,
      "mentions": [
        {
          "text": {
            "content": "Yearning for Zion",
            "beginOffset": 322
          }
        },
        {
          "text": {
            "content": "Yearning for Zion",
            "beginOffset": 1067
          }
        }
      ]
    },
    {
      "name": "Batchelor",
      "type": "PERSON",
      "metadata": {},
      "salience": 0.0030917565,
      "mentions": [
        {
          "text": {
            "content": "Batchelor",
            "beginOffset": 565
          }
        }
      ]
    },
    {
      "name": "New York times",
      "type": "ORGANIZATION",
      "metadata": {
        "wikipedia_url": "http://en.wikipedia.org/wiki/The_New_York_Times"
      },
      "salience": 0.0030002519,
      "mentions": [
        {
          "text": {
            "content": "New York times",
            "beginOffset": 690
          }
        }
      ]
    },
    {
      "name": "Ben Winslow",
      "type": "PERSON",
      "metadata": {},
      "salience": 0.0025627047,
      "mentions": [
        {
          "text": {
            "content": "Ben Winslow",
            "beginOffset": 576
          }
        }
      ]
    },
    {
      "name": "John Walsh",
      "type": "PERSON",
      "metadata": {
        "wikipedia_url": "http://en.wikipedia.org/wiki/John_Walsh_(rugby_league)"
      },
      "salience": 0.0025627047,
      "mentions": [
        {
          "text": {
            "content": "John Walsh",
            "beginOffset": 589
          }
        }
      ]
    },
    {
      "name": "Ayla Serenemoon",
      "type": "PERSON",
      "metadata": {},
      "salience": 0.0025627047,
      "mentions": [
        {
          "text": {
            "content": "Ayla Serenemoon",
            "beginOffset": 601
          }
        }
      ]
    },
    {
      "name": "Terry Roof",
      "type": "PERSON",
      "metadata": {},
      "salience": 0.0025627047,
      "mentions": [
        {
          "text": {
            "content": "Terry Roof",
            "beginOffset": 618
          }
        }
      ]
    },
    {
      "name": "&hellip",
      "type": "OTHER",
      "metadata": {},
      "salience": 0.0018824784,
      "mentions": [
        {
          "text": {
            "content": "&hellip",
            "beginOffset": 1102
          }
        }
      ]
    }
  ],
  "language": "en"
}
