{
  "entities": [
    {
      "name": "Harold Bloom",
      "type": "PERSON",
      "metadata": {
        "wikipedia_url": "http://en.wikipedia.org/wiki/Harold_Bloom"
      },
      "salience": 0.19829465,
      "mentions": [
        {
          "text": {
            "content": "Harold Bloom",
            "beginOffset": 121
          }
        },
        {
          "text": {
            "content": "Bloom",
            "beginOffset": 480
          }
        },
        {
          "text": {
            "content": "Harold Bloom",
            "beginOffset": 1449
          }
        }
      ]
    },
    {
      "name": "No Man Knows My History",
      "type": "WORK_OF_ART",
      "metadata": {
        "wikipedia_url": "http://en.wikipedia.org/wiki/No_Man_Knows_My_History"
      },
      "salience": 0.12226806,
      "mentions": [
        {
          "text": {
            "content": "No Man Knows My History",
            "beginOffset": 455
          }
        }
      ]
    },
    {
      "name": "Brother Joseph",
      "type": "PERSON",
      "metadata": {},
      "salience": 0.0856882,
      "mentions": [
        {
          "text": {
            "content": "Joseph Smith",
            "beginOffset": 4
          }
        },
        {
          "text": {
            "content": "Joseph Smith",
            "beginOffset": 57
          }
        },
        {
          "text": {
            "content": "Joseph",
            "beginOffset": 513
          }
        },
        {
          "text": {
            "content": "Brother Joseph",
            "beginOffset": 920
          }
        },
        {
          "text": {
            "content": "Joseph",
            "beginOffset": 1040
          }
        },
        {
          "text": {
            "content": "Joseph Smith",
            "beginOffset": 1385
          }
        }
      ]
    },
    {
      "name": "Joseph Smith&",
      "type": "PERSON",
      "metadata": {},
      "salience": 0.076085195,
      "mentions": [
        {
          "text": {
            "content": "Joseph Smith&",
            "beginOffset": 210
          }
        },
        {
          "text": {
            "content": "Joseph Smith&",
            "beginOffset": 362
          }
        },
        {
          "text": {
            "content": "Joseph Smith&",
            "beginOffset": 1538
          }
        },
        {
          "text": {
            "content": "Joseph Smith&",
            "beginOffset": 1690
          }
        }
      ]
    },
    {
      "name": "The American Religion",
      "type": "WORK_OF_ART",
      "metadata": {
        "wikipedia_url": "http://en.wikipedia.org/wiki/The_American_Religion"
      },
      "salience": 0.056529604,
      "mentions": [
        {
          "text": {
            "content": "The American Religion",
            "beginOffset": 165
          }
        },
        {
          "text": {
            "content": "The American Religion",
            "beginOffset": 1493
          }
        }
      ]
    },
    {
      "name": "Sunstone",
      "type": "ORGANIZATION",
      "metadata": {
        "wikipedia_url": "http://en.wikipedia.org/wiki/Sunstone_(magazine)"
      },
      "salience": 0.054271959,
      "mentions": [
        {
          "text": {
            "content": "Sunstone",
            "beginOffset": 321
          }
        },
        {
          "text": {
            "content": "Sunstone",
            "beginOffset": 383
          }
        },
        {
          "text": {
            "content": "Sunstone",
            "beginOffset": 1649
          }
        },
        {
          "text": {
            "content": "Sunstone",
            "beginOffset": 1711
          }
        }
      ]
    },
    {
      "name": "American",
      "type": "LOCATION",
      "metadata": {
        "wikipedia_url": "http://en.wikipedia.org/wiki/United_States"
      },
      "salience": 0.010813177,
      "mentions": [
        {
          "text": {
            "content": "American",
            "beginOffset": 248
          }
        },
        {
          "text": {
            "content": "American",
            "beginOffset": 1576
          }
        }
      ]
    },
    {
      "name": "Perspectivism",
      "type": "PERSON",
      "metadata": {},
      "salience": 0.010813177,
      "mentions": [
        {
          "text": {
            "content": "Perspectivism",
            "beginOffset": 344
          }
        },
        {
          "text": {
            "content": "Perspectivism",
            "beginOffset": 1672
          }
        }
      ]
    },
    {
      "name": "Fawn Brodie&",
      "type": "OTHER",
      "metadata": {},
      "salience": 0.010629918,
      "mentions": [
        {
          "text": {
            "content": "Fawn Brodie&",
            "beginOffset": 417
          }
        },
        {
          "text": {
            "content": "Fawn Brodie&",
            "beginOffset": 1745
          }
        }
      ]
    },
    {
      "name": "Yale",
      "type": "ORGANIZATION",
      "metadata": {
        "wikipedia_url": "http://en.wikipedia.org/wiki/Yale_University"
      },
      "salience": 0.0070423693,
      "mentions": [
        {
          "text": {
            "content": "Yale",
            "beginOffset": 106
          }
        },
        {
          "text": {
            "content": "Yale",
            "beginOffset": 1434
          }
        }
      ]
    },
    {
      "name": "Kovalenko",
      "type": "PERSON",
      "metadata": {},
      "salience": 0.0026808297,
      "mentions": [
        {
          "text": {
            "content": "Kovalenko",
            "beginOffset": 1022
          }
        }
      ]
    }
  ],
  "language": "en"
}
